{
  "type": "Feature",
  "stac_version": "1.0.0",
  "id": "DE_12064009",
  "properties": {
    "title": "CI_data",
    "description": "EU-wide high-resolution object-based maps of economic assets and infrastructure systems in coastal flood-prone areas.",
    "table:columns": [
      {
        "name": "type",
        "type": "string",
        "description": ""
      },
      {
        "name": "geometry",
        "type": "binary",
        "description": ""
      }
    ],
    "proj:bbox": [
      4620267.266262172,
      3274700.6748157116,
      4632772.000701336,
      3283194.256754965
    ],
    "proj:epsg": 3035,
    "table:row_count": 995,
    "created": "2025-04-08T09:37:37.674972Z",
    "datetime": "2021-08-01T00:00:00Z"
  },
  "geometry": {
    "type": "Polygon",
    "coordinates": [
      [
        [
          14.601603869339787,
          52.492987444711176
        ],
        [
          14.601603869339787,
          52.57610317961688
        ],
        [
          14.409839649683756,
          52.57610317961688
        ],
        [
          14.409839649683756,
          52.492987444711176
        ],
        [
          14.601603869339787,
          52.492987444711176
        ]
      ]
    ]
  },
  "links": [
    {
      "rel": "root",
      "href": "../../catalog.json",
      "type": "application/json",
      "title": "CoCliCo STAC Catalog"
    },
    {
      "rel": "collection",
      "href": "../collection.json",
      "type": "application/json",
      "title": "Critical Infrastructure"
    },
    {
      "rel": "parent",
      "href": "../collection.json",
      "type": "application/json",
      "title": "Critical Infrastructure"
    }
  ],
  "assets": {
    "data": {
      "href": "gs://coclico-data-public/coclico/LAU_ceed/DE_12064009.parquet",
      "type": "application/vnd.apache.parquet",
      "title": "CI_data",
      "description": "EU-wide high-resolution object-based maps of economic assets and infrastructure systems in coastal flood-prone areas.",
      "roles": [
        "data"
      ]
    },
    "visual": {
      "href": "https://coclico.avi.deltares.nl/geoserver/ceed_maps/wms?bbox={bbox-epsg-3857}&format=image/png&service=WMS&version=1.1.1&request=GetMap&srs=EPSG:3857&transparent=true&width=256&height=256&layers=ceed_maps:DE_12064009",
      "type": "application/png",
      "title": "ceed_maps:DE_12064009",
      "description": "OGS WMS url",
      "roles": [
        "visual"
      ]
    }
  },
  "bbox": [
    14.409839649683756,
    52.492987444711176,
    14.601603869339787,
    52.57610317961688
  ],
  "stac_extensions": [
    "https://stac-extensions.github.io/table/v1.2.0/schema.json",
    "https://stac-extensions.github.io/projection/v1.1.0/schema.json"
  ],
  "collection": "ceed_maps"
}