{
  "type": "Feature",
  "stac_version": "1.1.0",
  "stac_extensions": [
    "https://stac-extensions.github.io/projection/v2.0.0/schema.json",
    "https://stac-extensions.github.io/raster/v1.1.0/schema.json"
  ],
  "id": "6fb48b825b5f_n02e101-2eb39e",
  "geometry": {
    "type": "Polygon",
    "coordinates": [
      [
        [
          100.79855803882288,
          2.112576489803714
        ],
        [
          100.79855803882288,
          2.1308638629543437
        ],
        [
          100.78047023984027,
          2.1308638629543437
        ],
        [
          100.78047023984027,
          2.112576489803714
        ],
        [
          100.79855803882288,
          2.112576489803714
        ]
      ]
    ]
  },
  "bbox": [
    100.78047023984028,
    2.112576489803714,
    100.7985580388229,
    2.1308638629543437
  ],
  "properties": {
    "transect_id": "cl50888s01tr00207857",
    "lon": 100.78948211669922,
    "lat": 2.121717929840088,
    "user": "floris-calkoen",
    "uuid": "6fb48b825b5f",
    "datetime_created": "2024-10-24T13:19:01.339770+00:00",
    "datetime_updated": "2024-10-24T13:19:01.339770+00:00",
    "shore_type": "muddy_sediments",
    "coastal_type": "inlet",
    "landform_type": "N/A",
    "is_built_environment": "false",
    "has_defense": "false",
    "is_challenging": false,
    "comment": "",
    "link": "",
    "confidence": "medium",
    "is_validated": false,
    "utm_epsg": 32647,
    "continent": "AS",
    "country": "ID",
    "common_region_name": "Riau",
    "bearing": 277.7664794921875,
    "dist_b0": 22834.0,
    "dist_b30": 603.0,
    "dist_b60": 4687.0,
    "dist_b90": 148.0,
    "dist_b120": 25520.0,
    "dist_b150": 33327.0,
    "dist_b180": 56313.0,
    "dist_b210": 202596.0,
    "dist_b240": 548.0,
    "dist_b270": 159.0,
    "dist_b300": 4957.0,
    "dist_b330": 7573.0,
    "created": "2025-04-09T13:08:17.058506Z",
    "proj:code": "EPSG:32647",
    "proj:shape": [
      200,
      200
    ],
    "proj:transform": [
      10.049999999999999,
      0.0,
      698020.0,
      0.0,
      -10.1,
      235640.0,
      0.0,
      0.0,
      1.0
    ],
    "proj:bbox": [
      698020.0,
      233620.00000000003,
      700030.0,
      235640.0
    ],
    "proj:geometry": {
      "type": "Polygon",
      "coordinates": [
        [
          [
            700030.0,
            233620.00000000003
          ],
          [
            700030.0,
            235640.0
          ],
          [
            698020.0,
            235640.0
          ],
          [
            698020.0,
            233620.00000000003
          ],
          [
            700030.0,
            233620.00000000003
          ]
        ]
      ]
    },
    "datetime": "2021-04-22T00:00:00Z"
  },
  "links": [
    {
      "rel": "root",
      "href": "../../catalog.json",
      "type": "application/json",
      "title": "CoCliCo STAC Catalog"
    },
    {
      "rel": "collection",
      "href": "../collection.json",
      "type": "application/json",
      "title": "Typology Train"
    },
    {
      "rel": "parent",
      "href": "../collection.json",
      "type": "application/json",
      "title": "Typology Train"
    }
  ],
  "assets": {
    "blue": {
      "href": "https://coclico.blob.core.windows.net/typology/train/release/2025-04-09/imgs/6fb48b825b5f_n02e101-2eb39e_blue_10m.tif",
      "type": "image/tiff; application=geotiff; profile=cloud-optimized",
      "title": "blue band",
      "proj:code": "EPSG:32647",
      "proj:shape": [
        200,
        200
      ],
      "proj:transform": [
        10.049999999999999,
        0.0,
        698020.0,
        0.0,
        -10.1,
        235640.0,
        0.0,
        0.0,
        1.0
      ],
      "proj:bbox": [
        698020.0,
        233620.00000000003,
        700030.0,
        235640.0
      ],
      "proj:geometry": {
        "type": "Polygon",
        "coordinates": [
          [
            [
              700030.0,
              233620.00000000003
            ],
            [
              700030.0,
              235640.0
            ],
            [
              698020.0,
              235640.0
            ],
            [
              698020.0,
              233620.00000000003
            ],
            [
              700030.0,
              233620.00000000003
            ]
          ]
        ]
      },
      "raster:bands": [
        {
          "nodata": null,
          "data_type": "float32",
          "spatial_resolution": 10
        }
      ],
      "roles": [
        "data"
      ]
    },
    "green": {
      "href": "https://coclico.blob.core.windows.net/typology/train/release/2025-04-09/imgs/6fb48b825b5f_n02e101-2eb39e_green_10m.tif",
      "type": "image/tiff; application=geotiff; profile=cloud-optimized",
      "title": "green band",
      "proj:code": "EPSG:32647",
      "proj:shape": [
        200,
        200
      ],
      "proj:transform": [
        10.049999999999999,
        0.0,
        698020.0,
        0.0,
        -10.1,
        235640.0,
        0.0,
        0.0,
        1.0
      ],
      "proj:bbox": [
        698020.0,
        233620.00000000003,
        700030.0,
        235640.0
      ],
      "proj:geometry": {
        "type": "Polygon",
        "coordinates": [
          [
            [
              700030.0,
              233620.00000000003
            ],
            [
              700030.0,
              235640.0
            ],
            [
              698020.0,
              235640.0
            ],
            [
              698020.0,
              233620.00000000003
            ],
            [
              700030.0,
              233620.00000000003
            ]
          ]
        ]
      },
      "raster:bands": [
        {
          "nodata": null,
          "data_type": "float32",
          "spatial_resolution": 10
        }
      ],
      "roles": [
        "data"
      ]
    },
    "red": {
      "href": "https://coclico.blob.core.windows.net/typology/train/release/2025-04-09/imgs/6fb48b825b5f_n02e101-2eb39e_red_10m.tif",
      "type": "image/tiff; application=geotiff; profile=cloud-optimized",
      "title": "red band",
      "proj:code": "EPSG:32647",
      "proj:shape": [
        200,
        200
      ],
      "proj:transform": [
        10.049999999999999,
        0.0,
        698020.0,
        0.0,
        -10.1,
        235640.0,
        0.0,
        0.0,
        1.0
      ],
      "proj:bbox": [
        698020.0,
        233620.00000000003,
        700030.0,
        235640.0
      ],
      "proj:geometry": {
        "type": "Polygon",
        "coordinates": [
          [
            [
              700030.0,
              233620.00000000003
            ],
            [
              700030.0,
              235640.0
            ],
            [
              698020.0,
              235640.0
            ],
            [
              698020.0,
              233620.00000000003
            ],
            [
              700030.0,
              233620.00000000003
            ]
          ]
        ]
      },
      "raster:bands": [
        {
          "nodata": null,
          "data_type": "float32",
          "spatial_resolution": 10
        }
      ],
      "roles": [
        "data"
      ]
    },
    "nir": {
      "href": "https://coclico.blob.core.windows.net/typology/train/release/2025-04-09/imgs/6fb48b825b5f_n02e101-2eb39e_nir_10m.tif",
      "type": "image/tiff; application=geotiff; profile=cloud-optimized",
      "title": "nir band",
      "proj:code": "EPSG:32647",
      "proj:shape": [
        200,
        200
      ],
      "proj:transform": [
        10.049999999999999,
        0.0,
        698020.0,
        0.0,
        -10.1,
        235640.0,
        0.0,
        0.0,
        1.0
      ],
      "proj:bbox": [
        698020.0,
        233620.00000000003,
        700030.0,
        235640.0
      ],
      "proj:geometry": {
        "type": "Polygon",
        "coordinates": [
          [
            [
              700030.0,
              233620.00000000003
            ],
            [
              700030.0,
              235640.0
            ],
            [
              698020.0,
              235640.0
            ],
            [
              698020.0,
              233620.00000000003
            ],
            [
              700030.0,
              233620.00000000003
            ]
          ]
        ]
      },
      "raster:bands": [
        {
          "nodata": null,
          "data_type": "float32",
          "spatial_resolution": 10
        }
      ],
      "roles": [
        "data"
      ]
    },
    "swir16": {
      "href": "https://coclico.blob.core.windows.net/typology/train/release/2025-04-09/imgs/6fb48b825b5f_n02e101-2eb39e_swir16_10m.tif",
      "type": "image/tiff; application=geotiff; profile=cloud-optimized",
      "title": "swir16 band",
      "proj:code": "EPSG:32647",
      "proj:shape": [
        200,
        200
      ],
      "proj:transform": [
        10.049999999999999,
        0.0,
        698020.0,
        0.0,
        -10.1,
        235640.0,
        0.0,
        0.0,
        1.0
      ],
      "proj:bbox": [
        698020.0,
        233620.00000000003,
        700030.0,
        235640.0
      ],
      "proj:geometry": {
        "type": "Polygon",
        "coordinates": [
          [
            [
              700030.0,
              233620.00000000003
            ],
            [
              700030.0,
              235640.0
            ],
            [
              698020.0,
              235640.0
            ],
            [
              698020.0,
              233620.00000000003
            ],
            [
              700030.0,
              233620.00000000003
            ]
          ]
        ]
      },
      "raster:bands": [
        {
          "nodata": null,
          "data_type": "float32",
          "spatial_resolution": 10
        }
      ],
      "roles": [
        "data"
      ]
    },
    "swir22": {
      "href": "https://coclico.blob.core.windows.net/typology/train/release/2025-04-09/imgs/6fb48b825b5f_n02e101-2eb39e_swir22_10m.tif",
      "type": "image/tiff; application=geotiff; profile=cloud-optimized",
      "title": "swir22 band",
      "proj:code": "EPSG:32647",
      "proj:shape": [
        200,
        200
      ],
      "proj:transform": [
        10.049999999999999,
        0.0,
        698020.0,
        0.0,
        -10.1,
        235640.0,
        0.0,
        0.0,
        1.0
      ],
      "proj:bbox": [
        698020.0,
        233620.00000000003,
        700030.0,
        235640.0
      ],
      "proj:geometry": {
        "type": "Polygon",
        "coordinates": [
          [
            [
              700030.0,
              233620.00000000003
            ],
            [
              700030.0,
              235640.0
            ],
            [
              698020.0,
              235640.0
            ],
            [
              698020.0,
              233620.00000000003
            ],
            [
              700030.0,
              233620.00000000003
            ]
          ]
        ]
      },
      "raster:bands": [
        {
          "nodata": null,
          "data_type": "float32",
          "spatial_resolution": 10
        }
      ],
      "roles": [
        "data"
      ]
    },
    "NDWI": {
      "href": "https://coclico.blob.core.windows.net/typology/train/release/2025-04-09/imgs/6fb48b825b5f_n02e101-2eb39e_NDWI_10m.tif",
      "type": "image/tiff; application=geotiff; profile=cloud-optimized",
      "title": "NDWI band",
      "proj:code": "EPSG:32647",
      "proj:shape": [
        200,
        200
      ],
      "proj:transform": [
        10.049999999999999,
        0.0,
        698020.0,
        0.0,
        -10.1,
        235640.0,
        0.0,
        0.0,
        1.0
      ],
      "proj:bbox": [
        698020.0,
        233620.00000000003,
        700030.0,
        235640.0
      ],
      "proj:geometry": {
        "type": "Polygon",
        "coordinates": [
          [
            [
              700030.0,
              233620.00000000003
            ],
            [
              700030.0,
              235640.0
            ],
            [
              698020.0,
              235640.0
            ],
            [
              698020.0,
              233620.00000000003
            ],
            [
              700030.0,
              233620.00000000003
            ]
          ]
        ]
      },
      "raster:bands": [
        {
          "nodata": null,
          "data_type": "float32",
          "spatial_resolution": 10
        }
      ],
      "roles": [
        "data"
      ]
    },
    "NDVI": {
      "href": "https://coclico.blob.core.windows.net/typology/train/release/2025-04-09/imgs/6fb48b825b5f_n02e101-2eb39e_NDVI_10m.tif",
      "type": "image/tiff; application=geotiff; profile=cloud-optimized",
      "title": "NDVI band",
      "proj:code": "EPSG:32647",
      "proj:shape": [
        200,
        200
      ],
      "proj:transform": [
        10.049999999999999,
        0.0,
        698020.0,
        0.0,
        -10.1,
        235640.0,
        0.0,
        0.0,
        1.0
      ],
      "proj:bbox": [
        698020.0,
        233620.00000000003,
        700030.0,
        235640.0
      ],
      "proj:geometry": {
        "type": "Polygon",
        "coordinates": [
          [
            [
              700030.0,
              233620.00000000003
            ],
            [
              700030.0,
              235640.0
            ],
            [
              698020.0,
              235640.0
            ],
            [
              698020.0,
              233620.00000000003
            ],
            [
              700030.0,
              233620.00000000003
            ]
          ]
        ]
      },
      "raster:bands": [
        {
          "nodata": null,
          "data_type": "float32",
          "spatial_resolution": 10
        }
      ],
      "roles": [
        "data"
      ]
    },
    "MNDWI": {
      "href": "https://coclico.blob.core.windows.net/typology/train/release/2025-04-09/imgs/6fb48b825b5f_n02e101-2eb39e_MNDWI_10m.tif",
      "type": "image/tiff; application=geotiff; profile=cloud-optimized",
      "title": "MNDWI band",
      "proj:code": "EPSG:32647",
      "proj:shape": [
        200,
        200
      ],
      "proj:transform": [
        10.049999999999999,
        0.0,
        698020.0,
        0.0,
        -10.1,
        235640.0,
        0.0,
        0.0,
        1.0
      ],
      "proj:bbox": [
        698020.0,
        233620.00000000003,
        700030.0,
        235640.0
      ],
      "proj:geometry": {
        "type": "Polygon",
        "coordinates": [
          [
            [
              700030.0,
              233620.00000000003
            ],
            [
              700030.0,
              235640.0
            ],
            [
              698020.0,
              235640.0
            ],
            [
              698020.0,
              233620.00000000003
            ],
            [
              700030.0,
              233620.00000000003
            ]
          ]
        ]
      },
      "raster:bands": [
        {
          "nodata": null,
          "data_type": "float32",
          "spatial_resolution": 10
        }
      ],
      "roles": [
        "data"
      ]
    },
    "NDMI": {
      "href": "https://coclico.blob.core.windows.net/typology/train/release/2025-04-09/imgs/6fb48b825b5f_n02e101-2eb39e_NDMI_10m.tif",
      "type": "image/tiff; application=geotiff; profile=cloud-optimized",
      "title": "NDMI band",
      "proj:code": "EPSG:32647",
      "proj:shape": [
        200,
        200
      ],
      "proj:transform": [
        10.049999999999999,
        0.0,
        698020.0,
        0.0,
        -10.1,
        235640.0,
        0.0,
        0.0,
        1.0
      ],
      "proj:bbox": [
        698020.0,
        233620.00000000003,
        700030.0,
        235640.0
      ],
      "proj:geometry": {
        "type": "Polygon",
        "coordinates": [
          [
            [
              700030.0,
              233620.00000000003
            ],
            [
              700030.0,
              235640.0
            ],
            [
              698020.0,
              235640.0
            ],
            [
              698020.0,
              233620.00000000003
            ],
            [
              700030.0,
              233620.00000000003
            ]
          ]
        ]
      },
      "raster:bands": [
        {
          "nodata": null,
          "data_type": "float32",
          "spatial_resolution": 10
        }
      ],
      "roles": [
        "data"
      ]
    },
    "deltadtm": {
      "href": "https://coclico.blob.core.windows.net/typology/train/release/2025-04-09/imgs/6fb48b825b5f_n02e101-2eb39e_deltadtm_10m.tif",
      "type": "image/tiff; application=geotiff; profile=cloud-optimized",
      "title": "deltadtm band",
      "proj:code": "EPSG:32647",
      "proj:shape": [
        200,
        200
      ],
      "proj:transform": [
        10.049999999999999,
        0.0,
        698020.0,
        0.0,
        -10.1,
        235640.0,
        0.0,
        0.0,
        1.0
      ],
      "proj:bbox": [
        698020.0,
        233620.00000000003,
        700030.0,
        235640.0
      ],
      "proj:geometry": {
        "type": "Polygon",
        "coordinates": [
          [
            [
              700030.0,
              233620.00000000003
            ],
            [
              700030.0,
              235640.0
            ],
            [
              698020.0,
              235640.0
            ],
            [
              698020.0,
              233620.00000000003
            ],
            [
              700030.0,
              233620.00000000003
            ]
          ]
        ]
      },
      "raster:bands": [
        {
          "nodata": null,
          "data_type": "float32",
          "spatial_resolution": 10
        }
      ],
      "roles": [
        "data"
      ]
    },
    "cop_dem_glo_30": {
      "href": "https://coclico.blob.core.windows.net/typology/train/release/2025-04-09/imgs/6fb48b825b5f_n02e101-2eb39e_cop_dem_glo_30_10m.tif",
      "type": "image/tiff; application=geotiff; profile=cloud-optimized",
      "title": "cop_dem_glo_30 band",
      "proj:code": "EPSG:32647",
      "proj:shape": [
        200,
        200
      ],
      "proj:transform": [
        10.049999999999999,
        0.0,
        698020.0,
        0.0,
        -10.1,
        235640.0,
        0.0,
        0.0,
        1.0
      ],
      "proj:bbox": [
        698020.0,
        233620.00000000003,
        700030.0,
        235640.0
      ],
      "proj:geometry": {
        "type": "Polygon",
        "coordinates": [
          [
            [
              700030.0,
              233620.00000000003
            ],
            [
              700030.0,
              235640.0
            ],
            [
              698020.0,
              235640.0
            ],
            [
              698020.0,
              233620.00000000003
            ],
            [
              700030.0,
              233620.00000000003
            ]
          ]
        ]
      },
      "raster:bands": [
        {
          "nodata": null,
          "data_type": "float32",
          "spatial_resolution": 10
        }
      ],
      "roles": [
        "data"
      ]
    },
    "region_of_interest": {
      "href": "https://coclico.blob.core.windows.net/typology/train/release/2025-04-09/imgs/6fb48b825b5f_n02e101-2eb39e_region_of_interest_10m.tif",
      "type": "image/tiff; application=geotiff; profile=cloud-optimized",
      "title": "region_of_interest band",
      "proj:code": "EPSG:32647",
      "proj:shape": [
        200,
        200
      ],
      "proj:transform": [
        10.049999999999999,
        0.0,
        698020.0,
        0.0,
        -10.1,
        235640.0,
        0.0,
        0.0,
        1.0
      ],
      "proj:bbox": [
        698020.0,
        233620.00000000003,
        700030.0,
        235640.0
      ],
      "proj:geometry": {
        "type": "Polygon",
        "coordinates": [
          [
            [
              700030.0,
              233620.00000000003
            ],
            [
              700030.0,
              235640.0
            ],
            [
              698020.0,
              235640.0
            ],
            [
              698020.0,
              233620.00000000003
            ],
            [
              700030.0,
              233620.00000000003
            ]
          ]
        ]
      },
      "raster:bands": [
        {
          "nodata": null,
          "data_type": "float32",
          "spatial_resolution": 10
        }
      ],
      "roles": [
        "data"
      ]
    }
  },
  "collection": "typology-train"
}