{
  "type": "Feature",
  "stac_version": "1.1.0",
  "stac_extensions": [
    "https://stac-extensions.github.io/projection/v2.0.0/schema.json",
    "https://stac-extensions.github.io/raster/v1.1.0/schema.json"
  ],
  "id": "ebe13af64481_n54e08-622e7c",
  "geometry": {
    "type": "Polygon",
    "coordinates": [
      [
        [
          7.915974402910109,
          53.773962167079524
        ],
        [
          7.915974402910109,
          53.79258014034931
        ],
        [
          7.884388014325282,
          53.79258014034931
        ],
        [
          7.884388014325282,
          53.773962167079524
        ],
        [
          7.915974402910109,
          53.773962167079524
        ]
      ]
    ]
  },
  "bbox": [
    7.884388014325272,
    53.773962167079524,
    7.915974402910099,
    53.79258014034931
  ],
  "properties": {
    "transect_id": "cl32618s00tr00005338",
    "lon": 7.900187969207764,
    "lat": 53.78322982788086,
    "user": "floris-calkoen",
    "uuid": "ebe13af64481",
    "datetime_created": "2024-10-24T08:17:18.667499+00:00",
    "datetime_updated": "2025-02-08T15:27:25.687440+00:00",
    "shore_type": "muddy_sediments",
    "coastal_type": "sediment_plain",
    "landform_type": "N/A",
    "is_built_environment": "true",
    "has_defense": "true",
    "is_challenging": false,
    "comment": "",
    "link": "",
    "confidence": "medium",
    "is_validated": true,
    "utm_epsg": 32632,
    "continent": "EU",
    "country": "DE",
    "common_region_name": "Lower Saxony",
    "bearing": 201.66062927246094,
    "dist_b0": 8330.0,
    "dist_b30": 14685.0,
    "dist_b60": 2038.0,
    "dist_b90": 1237.0,
    "dist_b120": 1572.0,
    "dist_b150": 1202.0,
    "dist_b180": 1201.0,
    "dist_b210": 1552.0,
    "dist_b240": 3122.0,
    "dist_b270": 7703.0,
    "dist_b300": 9766.0,
    "dist_b330": 7496.0,
    "created": "2025-04-09T12:03:21.818340Z",
    "proj:code": "EPSG:32632",
    "proj:shape": [
      200,
      200
    ],
    "proj:transform": [
      10.25,
      0.0,
      426510.0,
      0.0,
      -10.2,
      5960990.0,
      0.0,
      0.0,
      1.0
    ],
    "proj:bbox": [
      426510.0,
      5958950.000000001,
      428560.0,
      5960990.0
    ],
    "proj:geometry": {
      "type": "Polygon",
      "coordinates": [
        [
          [
            428560.0,
            5958950.000000001
          ],
          [
            428560.0,
            5960990.0
          ],
          [
            426510.0,
            5960990.0
          ],
          [
            426510.0,
            5958950.000000001
          ],
          [
            428560.0,
            5958950.000000001
          ]
        ]
      ]
    },
    "datetime": "2021-04-22T00:00:00Z"
  },
  "links": [
    {
      "rel": "root",
      "href": "../../catalog.json",
      "type": "application/json",
      "title": "CoCliCo STAC Catalog"
    },
    {
      "rel": "collection",
      "href": "../collection.json",
      "type": "application/json",
      "title": "Typology Train"
    },
    {
      "rel": "parent",
      "href": "../collection.json",
      "type": "application/json",
      "title": "Typology Train"
    }
  ],
  "assets": {
    "blue": {
      "href": "https://coclico.blob.core.windows.net/typology/train/release/2025-04-09/imgs/ebe13af64481_n54e08-622e7c_blue_10m.tif",
      "type": "image/tiff; application=geotiff; profile=cloud-optimized",
      "title": "blue band",
      "proj:code": "EPSG:32632",
      "proj:shape": [
        200,
        200
      ],
      "proj:transform": [
        10.25,
        0.0,
        426510.0,
        0.0,
        -10.2,
        5960990.0,
        0.0,
        0.0,
        1.0
      ],
      "proj:bbox": [
        426510.0,
        5958950.000000001,
        428560.0,
        5960990.0
      ],
      "proj:geometry": {
        "type": "Polygon",
        "coordinates": [
          [
            [
              428560.0,
              5958950.000000001
            ],
            [
              428560.0,
              5960990.0
            ],
            [
              426510.0,
              5960990.0
            ],
            [
              426510.0,
              5958950.000000001
            ],
            [
              428560.0,
              5958950.000000001
            ]
          ]
        ]
      },
      "raster:bands": [
        {
          "nodata": null,
          "data_type": "float32",
          "spatial_resolution": 10
        }
      ],
      "roles": [
        "data"
      ]
    },
    "green": {
      "href": "https://coclico.blob.core.windows.net/typology/train/release/2025-04-09/imgs/ebe13af64481_n54e08-622e7c_green_10m.tif",
      "type": "image/tiff; application=geotiff; profile=cloud-optimized",
      "title": "green band",
      "proj:code": "EPSG:32632",
      "proj:shape": [
        200,
        200
      ],
      "proj:transform": [
        10.25,
        0.0,
        426510.0,
        0.0,
        -10.2,
        5960990.0,
        0.0,
        0.0,
        1.0
      ],
      "proj:bbox": [
        426510.0,
        5958950.000000001,
        428560.0,
        5960990.0
      ],
      "proj:geometry": {
        "type": "Polygon",
        "coordinates": [
          [
            [
              428560.0,
              5958950.000000001
            ],
            [
              428560.0,
              5960990.0
            ],
            [
              426510.0,
              5960990.0
            ],
            [
              426510.0,
              5958950.000000001
            ],
            [
              428560.0,
              5958950.000000001
            ]
          ]
        ]
      },
      "raster:bands": [
        {
          "nodata": null,
          "data_type": "float32",
          "spatial_resolution": 10
        }
      ],
      "roles": [
        "data"
      ]
    },
    "red": {
      "href": "https://coclico.blob.core.windows.net/typology/train/release/2025-04-09/imgs/ebe13af64481_n54e08-622e7c_red_10m.tif",
      "type": "image/tiff; application=geotiff; profile=cloud-optimized",
      "title": "red band",
      "proj:code": "EPSG:32632",
      "proj:shape": [
        200,
        200
      ],
      "proj:transform": [
        10.25,
        0.0,
        426510.0,
        0.0,
        -10.2,
        5960990.0,
        0.0,
        0.0,
        1.0
      ],
      "proj:bbox": [
        426510.0,
        5958950.000000001,
        428560.0,
        5960990.0
      ],
      "proj:geometry": {
        "type": "Polygon",
        "coordinates": [
          [
            [
              428560.0,
              5958950.000000001
            ],
            [
              428560.0,
              5960990.0
            ],
            [
              426510.0,
              5960990.0
            ],
            [
              426510.0,
              5958950.000000001
            ],
            [
              428560.0,
              5958950.000000001
            ]
          ]
        ]
      },
      "raster:bands": [
        {
          "nodata": null,
          "data_type": "float32",
          "spatial_resolution": 10
        }
      ],
      "roles": [
        "data"
      ]
    },
    "nir": {
      "href": "https://coclico.blob.core.windows.net/typology/train/release/2025-04-09/imgs/ebe13af64481_n54e08-622e7c_nir_10m.tif",
      "type": "image/tiff; application=geotiff; profile=cloud-optimized",
      "title": "nir band",
      "proj:code": "EPSG:32632",
      "proj:shape": [
        200,
        200
      ],
      "proj:transform": [
        10.25,
        0.0,
        426510.0,
        0.0,
        -10.2,
        5960990.0,
        0.0,
        0.0,
        1.0
      ],
      "proj:bbox": [
        426510.0,
        5958950.000000001,
        428560.0,
        5960990.0
      ],
      "proj:geometry": {
        "type": "Polygon",
        "coordinates": [
          [
            [
              428560.0,
              5958950.000000001
            ],
            [
              428560.0,
              5960990.0
            ],
            [
              426510.0,
              5960990.0
            ],
            [
              426510.0,
              5958950.000000001
            ],
            [
              428560.0,
              5958950.000000001
            ]
          ]
        ]
      },
      "raster:bands": [
        {
          "nodata": null,
          "data_type": "float32",
          "spatial_resolution": 10
        }
      ],
      "roles": [
        "data"
      ]
    },
    "swir16": {
      "href": "https://coclico.blob.core.windows.net/typology/train/release/2025-04-09/imgs/ebe13af64481_n54e08-622e7c_swir16_10m.tif",
      "type": "image/tiff; application=geotiff; profile=cloud-optimized",
      "title": "swir16 band",
      "proj:code": "EPSG:32632",
      "proj:shape": [
        200,
        200
      ],
      "proj:transform": [
        10.25,
        0.0,
        426510.0,
        0.0,
        -10.2,
        5960990.0,
        0.0,
        0.0,
        1.0
      ],
      "proj:bbox": [
        426510.0,
        5958950.000000001,
        428560.0,
        5960990.0
      ],
      "proj:geometry": {
        "type": "Polygon",
        "coordinates": [
          [
            [
              428560.0,
              5958950.000000001
            ],
            [
              428560.0,
              5960990.0
            ],
            [
              426510.0,
              5960990.0
            ],
            [
              426510.0,
              5958950.000000001
            ],
            [
              428560.0,
              5958950.000000001
            ]
          ]
        ]
      },
      "raster:bands": [
        {
          "nodata": null,
          "data_type": "float32",
          "spatial_resolution": 10
        }
      ],
      "roles": [
        "data"
      ]
    },
    "swir22": {
      "href": "https://coclico.blob.core.windows.net/typology/train/release/2025-04-09/imgs/ebe13af64481_n54e08-622e7c_swir22_10m.tif",
      "type": "image/tiff; application=geotiff; profile=cloud-optimized",
      "title": "swir22 band",
      "proj:code": "EPSG:32632",
      "proj:shape": [
        200,
        200
      ],
      "proj:transform": [
        10.25,
        0.0,
        426510.0,
        0.0,
        -10.2,
        5960990.0,
        0.0,
        0.0,
        1.0
      ],
      "proj:bbox": [
        426510.0,
        5958950.000000001,
        428560.0,
        5960990.0
      ],
      "proj:geometry": {
        "type": "Polygon",
        "coordinates": [
          [
            [
              428560.0,
              5958950.000000001
            ],
            [
              428560.0,
              5960990.0
            ],
            [
              426510.0,
              5960990.0
            ],
            [
              426510.0,
              5958950.000000001
            ],
            [
              428560.0,
              5958950.000000001
            ]
          ]
        ]
      },
      "raster:bands": [
        {
          "nodata": null,
          "data_type": "float32",
          "spatial_resolution": 10
        }
      ],
      "roles": [
        "data"
      ]
    },
    "NDWI": {
      "href": "https://coclico.blob.core.windows.net/typology/train/release/2025-04-09/imgs/ebe13af64481_n54e08-622e7c_NDWI_10m.tif",
      "type": "image/tiff; application=geotiff; profile=cloud-optimized",
      "title": "NDWI band",
      "proj:code": "EPSG:32632",
      "proj:shape": [
        200,
        200
      ],
      "proj:transform": [
        10.25,
        0.0,
        426510.0,
        0.0,
        -10.2,
        5960990.0,
        0.0,
        0.0,
        1.0
      ],
      "proj:bbox": [
        426510.0,
        5958950.000000001,
        428560.0,
        5960990.0
      ],
      "proj:geometry": {
        "type": "Polygon",
        "coordinates": [
          [
            [
              428560.0,
              5958950.000000001
            ],
            [
              428560.0,
              5960990.0
            ],
            [
              426510.0,
              5960990.0
            ],
            [
              426510.0,
              5958950.000000001
            ],
            [
              428560.0,
              5958950.000000001
            ]
          ]
        ]
      },
      "raster:bands": [
        {
          "nodata": null,
          "data_type": "float32",
          "spatial_resolution": 10
        }
      ],
      "roles": [
        "data"
      ]
    },
    "NDVI": {
      "href": "https://coclico.blob.core.windows.net/typology/train/release/2025-04-09/imgs/ebe13af64481_n54e08-622e7c_NDVI_10m.tif",
      "type": "image/tiff; application=geotiff; profile=cloud-optimized",
      "title": "NDVI band",
      "proj:code": "EPSG:32632",
      "proj:shape": [
        200,
        200
      ],
      "proj:transform": [
        10.25,
        0.0,
        426510.0,
        0.0,
        -10.2,
        5960990.0,
        0.0,
        0.0,
        1.0
      ],
      "proj:bbox": [
        426510.0,
        5958950.000000001,
        428560.0,
        5960990.0
      ],
      "proj:geometry": {
        "type": "Polygon",
        "coordinates": [
          [
            [
              428560.0,
              5958950.000000001
            ],
            [
              428560.0,
              5960990.0
            ],
            [
              426510.0,
              5960990.0
            ],
            [
              426510.0,
              5958950.000000001
            ],
            [
              428560.0,
              5958950.000000001
            ]
          ]
        ]
      },
      "raster:bands": [
        {
          "nodata": null,
          "data_type": "float32",
          "spatial_resolution": 10
        }
      ],
      "roles": [
        "data"
      ]
    },
    "MNDWI": {
      "href": "https://coclico.blob.core.windows.net/typology/train/release/2025-04-09/imgs/ebe13af64481_n54e08-622e7c_MNDWI_10m.tif",
      "type": "image/tiff; application=geotiff; profile=cloud-optimized",
      "title": "MNDWI band",
      "proj:code": "EPSG:32632",
      "proj:shape": [
        200,
        200
      ],
      "proj:transform": [
        10.25,
        0.0,
        426510.0,
        0.0,
        -10.2,
        5960990.0,
        0.0,
        0.0,
        1.0
      ],
      "proj:bbox": [
        426510.0,
        5958950.000000001,
        428560.0,
        5960990.0
      ],
      "proj:geometry": {
        "type": "Polygon",
        "coordinates": [
          [
            [
              428560.0,
              5958950.000000001
            ],
            [
              428560.0,
              5960990.0
            ],
            [
              426510.0,
              5960990.0
            ],
            [
              426510.0,
              5958950.000000001
            ],
            [
              428560.0,
              5958950.000000001
            ]
          ]
        ]
      },
      "raster:bands": [
        {
          "nodata": null,
          "data_type": "float32",
          "spatial_resolution": 10
        }
      ],
      "roles": [
        "data"
      ]
    },
    "NDMI": {
      "href": "https://coclico.blob.core.windows.net/typology/train/release/2025-04-09/imgs/ebe13af64481_n54e08-622e7c_NDMI_10m.tif",
      "type": "image/tiff; application=geotiff; profile=cloud-optimized",
      "title": "NDMI band",
      "proj:code": "EPSG:32632",
      "proj:shape": [
        200,
        200
      ],
      "proj:transform": [
        10.25,
        0.0,
        426510.0,
        0.0,
        -10.2,
        5960990.0,
        0.0,
        0.0,
        1.0
      ],
      "proj:bbox": [
        426510.0,
        5958950.000000001,
        428560.0,
        5960990.0
      ],
      "proj:geometry": {
        "type": "Polygon",
        "coordinates": [
          [
            [
              428560.0,
              5958950.000000001
            ],
            [
              428560.0,
              5960990.0
            ],
            [
              426510.0,
              5960990.0
            ],
            [
              426510.0,
              5958950.000000001
            ],
            [
              428560.0,
              5958950.000000001
            ]
          ]
        ]
      },
      "raster:bands": [
        {
          "nodata": null,
          "data_type": "float32",
          "spatial_resolution": 10
        }
      ],
      "roles": [
        "data"
      ]
    },
    "deltadtm": {
      "href": "https://coclico.blob.core.windows.net/typology/train/release/2025-04-09/imgs/ebe13af64481_n54e08-622e7c_deltadtm_10m.tif",
      "type": "image/tiff; application=geotiff; profile=cloud-optimized",
      "title": "deltadtm band",
      "proj:code": "EPSG:32632",
      "proj:shape": [
        200,
        200
      ],
      "proj:transform": [
        10.25,
        0.0,
        426510.0,
        0.0,
        -10.2,
        5960990.0,
        0.0,
        0.0,
        1.0
      ],
      "proj:bbox": [
        426510.0,
        5958950.000000001,
        428560.0,
        5960990.0
      ],
      "proj:geometry": {
        "type": "Polygon",
        "coordinates": [
          [
            [
              428560.0,
              5958950.000000001
            ],
            [
              428560.0,
              5960990.0
            ],
            [
              426510.0,
              5960990.0
            ],
            [
              426510.0,
              5958950.000000001
            ],
            [
              428560.0,
              5958950.000000001
            ]
          ]
        ]
      },
      "raster:bands": [
        {
          "nodata": null,
          "data_type": "float32",
          "spatial_resolution": 10
        }
      ],
      "roles": [
        "data"
      ]
    },
    "cop_dem_glo_30": {
      "href": "https://coclico.blob.core.windows.net/typology/train/release/2025-04-09/imgs/ebe13af64481_n54e08-622e7c_cop_dem_glo_30_10m.tif",
      "type": "image/tiff; application=geotiff; profile=cloud-optimized",
      "title": "cop_dem_glo_30 band",
      "proj:code": "EPSG:32632",
      "proj:shape": [
        200,
        200
      ],
      "proj:transform": [
        10.25,
        0.0,
        426510.0,
        0.0,
        -10.2,
        5960990.0,
        0.0,
        0.0,
        1.0
      ],
      "proj:bbox": [
        426510.0,
        5958950.000000001,
        428560.0,
        5960990.0
      ],
      "proj:geometry": {
        "type": "Polygon",
        "coordinates": [
          [
            [
              428560.0,
              5958950.000000001
            ],
            [
              428560.0,
              5960990.0
            ],
            [
              426510.0,
              5960990.0
            ],
            [
              426510.0,
              5958950.000000001
            ],
            [
              428560.0,
              5958950.000000001
            ]
          ]
        ]
      },
      "raster:bands": [
        {
          "nodata": null,
          "data_type": "float32",
          "spatial_resolution": 10
        }
      ],
      "roles": [
        "data"
      ]
    },
    "region_of_interest": {
      "href": "https://coclico.blob.core.windows.net/typology/train/release/2025-04-09/imgs/ebe13af64481_n54e08-622e7c_region_of_interest_10m.tif",
      "type": "image/tiff; application=geotiff; profile=cloud-optimized",
      "title": "region_of_interest band",
      "proj:code": "EPSG:32632",
      "proj:shape": [
        200,
        200
      ],
      "proj:transform": [
        10.25,
        0.0,
        426510.0,
        0.0,
        -10.2,
        5960990.0,
        0.0,
        0.0,
        1.0
      ],
      "proj:bbox": [
        426510.0,
        5958950.000000001,
        428560.0,
        5960990.0
      ],
      "proj:geometry": {
        "type": "Polygon",
        "coordinates": [
          [
            [
              428560.0,
              5958950.000000001
            ],
            [
              428560.0,
              5960990.0
            ],
            [
              426510.0,
              5960990.0
            ],
            [
              426510.0,
              5958950.000000001
            ],
            [
              428560.0,
              5958950.000000001
            ]
          ]
        ]
      },
      "raster:bands": [
        {
          "nodata": null,
          "data_type": "float32",
          "spatial_resolution": 10
        }
      ],
      "roles": [
        "data"
      ]
    }
  },
  "collection": "typology-train"
}