{
  "type": "Feature",
  "stac_version": "1.1.0",
  "stac_extensions": [
    "https://stac-extensions.github.io/projection/v2.0.0/schema.json",
    "https://stac-extensions.github.io/raster/v1.1.0/schema.json"
  ],
  "id": "22WES_z9-n65w051-73cc3d_20230101_20240101",
  "geometry": {
    "type": "Polygon",
    "coordinates": [
      [
        [
          -49.922614674850735,
          64.7706908062237
        ],
        [
          -49.922614674850735,
          64.92124432933699
        ],
        [
          -50.62716326983505,
          64.92124432933699
        ],
        [
          -50.62716326983505,
          64.7706908062237
        ],
        [
          -49.922614674850735,
          64.7706908062237
        ]
      ]
    ]
  },
  "bbox": [
    -50.62716326983505,
    64.7706908062237,
    -49.92261467485074,
    64.92124432933699
  ],
  "properties": {
    "AREA_OR_POINT": "Area",
    "composite_avg_interval": "8 days 05:08:36.071392857",
    "composite_determination_method": "CoastPy Simple Median",
    "composite_n_obs": 29,
    "composite_stac_ids": "['S2B_MSIL2A_20230806T150809_R025_T22WES_20230806T211805', 'S2A_MSIL2A_20230811T150951_R025_T22WES_20230812T002252', 'S2A_MSIL2A_20230930T151031_R025_T22WES_20230930T221501', 'S2A_MSIL2A_20231020T151241_R025_T22WES_20231020T224648', 'S2B_MSIL2A_20230309T150959_R025_T22WES_20240823T102323', 'S2B_MSIL2A_20230617T150809_R025_T22WES_20230617T212907', 'S2B_MSIL2A_20230428T150759_R025_T22WES_20230428T212750', 'S2A_MSIL2A_20230712T150951_R025_T22WES_20230712T233446', 'S2A_MSIL2A_20230413T150801_R025_T22WES_20230414T001306', 'S2A_MSIL2A_20230702T150801_R025_T22WES_20230702T222619', 'S2B_MSIL2A_20231009T145029_R082_T22WES_20231009T203249', 'S2B_MSIL2A_20230412T144749_R082_T22WES_20230412T212923', 'S2A_MSIL2A_20230815T144951_R082_T22WES_20230815T223159', 'S2A_MSIL2A_20230517T144751_R082_T22WES_20230517T223208', 'S2B_MSIL2A_20230402T144759_R082_T22WES_20230402T202752', 'S2A_MSIL2A_20230427T144751_R082_T22WES_20230427T214647', 'S2A_MSIL2A_20230726T144751_R082_T22WES_20230726T222803', 'S2A_MSIL2A_20230308T145041_R082_T22WES_20230308T211556', 'S2B_MSIL2A_20230909T144759_R082_T22WES_20230909T192805', 'S2B_MSIL2A_20230306T150109_R125_T22WES_20240820T043706', 'S2A_MSIL2A_20230808T145951_R125_T22WES_20230808T231502', 'S2B_MSIL2A_20230724T145759_R125_T22WES_20230724T211420', 'S2A_MSIL2A_20230818T145801_R125_T22WES_20230818T233053', 'S2A_MSIL2A_20230311T150021_R125_T22WES_20230311T212154', 'S2B_MSIL2A_20230405T145759_R125_T22WES_20230406T072612', 'S2B_MSIL2A_20231022T150159_R125_T22WES_20231022T202027', 'S2B_MSIL2A_20230505T145759_R125_T22WES_20230505T192804', 'S2B_MSIL2A_20230316T145859_R125_T22WES_20230316T213159', 'S2B_MSIL2A_20230922T145829_R125_T22WES_20230922T214835']",
    "composite_summary": "Composite dataset created by taking the median value of each pixel across all time steps.",
    "eo_cloud_cover": 7,
    "start_datetime": "2023-03-06T15:01:09.025000Z",
    "end_datetime": "2023-10-22T15:01:59.024000Z",
    "created": "2025-03-01T14:57:11.915133Z",
    "proj:code": "EPSG:32622",
    "proj:shape": [
      1640,
      3323
    ],
    "proj:transform": [
      10.0,
      0.0,
      517730.0,
      0.0,
      -10.0,
      7199730.0,
      0.0,
      0.0,
      1.0
    ],
    "proj:bbox": [
      517730.0,
      7183330.0,
      550960.0,
      7199730.0
    ],
    "proj:geometry": {
      "type": "Polygon",
      "coordinates": [
        [
          [
            550960.0,
            7183330.0
          ],
          [
            550960.0,
            7199730.0
          ],
          [
            517730.0,
            7199730.0
          ],
          [
            517730.0,
            7183330.0
          ],
          [
            550960.0,
            7183330.0
          ]
        ]
      ]
    },
    "datetime": "2023-03-06T15:01:09.025000Z"
  },
  "links": [
    {
      "rel": "root",
      "href": "../../catalog.json",
      "type": "application/json",
      "title": "CoCliCo STAC Catalog"
    },
    {
      "rel": "collection",
      "href": "../collection.json",
      "type": "application/json",
      "title": "Sentinel-2 L2A Annual Composites"
    },
    {
      "rel": "parent",
      "href": "../collection.json",
      "type": "application/json",
      "title": "Sentinel-2 L2A Annual Composites"
    }
  ],
  "assets": {
    "blue": {
      "href": "https://coclico.blob.core.windows.net/tmp/s2-l2a-composite/release/2025-01-17/22WES_z9-n65w051-73cc3d_20230101_20240101_blue_10m.tif",
      "type": "image/tiff; application=geotiff; profile=cloud-optimized",
      "title": "blue band",
      "proj:code": "EPSG:32622",
      "proj:shape": [
        1640,
        3323
      ],
      "proj:transform": [
        10.0,
        0.0,
        517730.0,
        0.0,
        -10.0,
        7199730.0,
        0.0,
        0.0,
        1.0
      ],
      "proj:bbox": [
        517730.0,
        7183330.0,
        550960.0,
        7199730.0
      ],
      "proj:geometry": {
        "type": "Polygon",
        "coordinates": [
          [
            [
              550960.0,
              7183330.0
            ],
            [
              550960.0,
              7199730.0
            ],
            [
              517730.0,
              7199730.0
            ],
            [
              517730.0,
              7183330.0
            ],
            [
              550960.0,
              7183330.0
            ]
          ]
        ]
      },
      "raster:bands": [
        {
          "nodata": -9999,
          "data_type": "int16",
          "spatial_resolution": 10,
          "unit": "m",
          "scale": 0.0001
        }
      ],
      "roles": [
        "data"
      ]
    },
    "green": {
      "href": "https://coclico.blob.core.windows.net/tmp/s2-l2a-composite/release/2025-01-17/22WES_z9-n65w051-73cc3d_20230101_20240101_green_10m.tif",
      "type": "image/tiff; application=geotiff; profile=cloud-optimized",
      "title": "green band",
      "proj:code": "EPSG:32622",
      "proj:shape": [
        1640,
        3323
      ],
      "proj:transform": [
        10.0,
        0.0,
        517730.0,
        0.0,
        -10.0,
        7199730.0,
        0.0,
        0.0,
        1.0
      ],
      "proj:bbox": [
        517730.0,
        7183330.0,
        550960.0,
        7199730.0
      ],
      "proj:geometry": {
        "type": "Polygon",
        "coordinates": [
          [
            [
              550960.0,
              7183330.0
            ],
            [
              550960.0,
              7199730.0
            ],
            [
              517730.0,
              7199730.0
            ],
            [
              517730.0,
              7183330.0
            ],
            [
              550960.0,
              7183330.0
            ]
          ]
        ]
      },
      "raster:bands": [
        {
          "nodata": -9999,
          "data_type": "int16",
          "spatial_resolution": 10,
          "unit": "m",
          "scale": 0.0001
        }
      ],
      "roles": [
        "data"
      ]
    },
    "nir": {
      "href": "https://coclico.blob.core.windows.net/tmp/s2-l2a-composite/release/2025-01-17/22WES_z9-n65w051-73cc3d_20230101_20240101_nir_10m.tif",
      "type": "image/tiff; application=geotiff; profile=cloud-optimized",
      "title": "nir band",
      "proj:code": "EPSG:32622",
      "proj:shape": [
        1640,
        3323
      ],
      "proj:transform": [
        10.0,
        0.0,
        517730.0,
        0.0,
        -10.0,
        7199730.0,
        0.0,
        0.0,
        1.0
      ],
      "proj:bbox": [
        517730.0,
        7183330.0,
        550960.0,
        7199730.0
      ],
      "proj:geometry": {
        "type": "Polygon",
        "coordinates": [
          [
            [
              550960.0,
              7183330.0
            ],
            [
              550960.0,
              7199730.0
            ],
            [
              517730.0,
              7199730.0
            ],
            [
              517730.0,
              7183330.0
            ],
            [
              550960.0,
              7183330.0
            ]
          ]
        ]
      },
      "raster:bands": [
        {
          "nodata": -9999,
          "data_type": "int16",
          "spatial_resolution": 10,
          "unit": "m",
          "scale": 0.0001
        }
      ],
      "roles": [
        "data"
      ]
    },
    "red": {
      "href": "https://coclico.blob.core.windows.net/tmp/s2-l2a-composite/release/2025-01-17/22WES_z9-n65w051-73cc3d_20230101_20240101_red_10m.tif",
      "type": "image/tiff; application=geotiff; profile=cloud-optimized",
      "title": "red band",
      "proj:code": "EPSG:32622",
      "proj:shape": [
        1640,
        3323
      ],
      "proj:transform": [
        10.0,
        0.0,
        517730.0,
        0.0,
        -10.0,
        7199730.0,
        0.0,
        0.0,
        1.0
      ],
      "proj:bbox": [
        517730.0,
        7183330.0,
        550960.0,
        7199730.0
      ],
      "proj:geometry": {
        "type": "Polygon",
        "coordinates": [
          [
            [
              550960.0,
              7183330.0
            ],
            [
              550960.0,
              7199730.0
            ],
            [
              517730.0,
              7199730.0
            ],
            [
              517730.0,
              7183330.0
            ],
            [
              550960.0,
              7183330.0
            ]
          ]
        ]
      },
      "raster:bands": [
        {
          "nodata": -9999,
          "data_type": "int16",
          "spatial_resolution": 10,
          "unit": "m",
          "scale": 0.0001
        }
      ],
      "roles": [
        "data"
      ]
    },
    "swir16": {
      "href": "https://coclico.blob.core.windows.net/tmp/s2-l2a-composite/release/2025-01-17/22WES_z9-n65w051-73cc3d_20230101_20240101_swir16_10m.tif",
      "type": "image/tiff; application=geotiff; profile=cloud-optimized",
      "title": "swir16 band",
      "proj:code": "EPSG:32622",
      "proj:shape": [
        1640,
        3323
      ],
      "proj:transform": [
        10.0,
        0.0,
        517730.0,
        0.0,
        -10.0,
        7199730.0,
        0.0,
        0.0,
        1.0
      ],
      "proj:bbox": [
        517730.0,
        7183330.0,
        550960.0,
        7199730.0
      ],
      "proj:geometry": {
        "type": "Polygon",
        "coordinates": [
          [
            [
              550960.0,
              7183330.0
            ],
            [
              550960.0,
              7199730.0
            ],
            [
              517730.0,
              7199730.0
            ],
            [
              517730.0,
              7183330.0
            ],
            [
              550960.0,
              7183330.0
            ]
          ]
        ]
      },
      "raster:bands": [
        {
          "nodata": -9999,
          "data_type": "int16",
          "spatial_resolution": 10,
          "unit": "m",
          "scale": 0.0001
        }
      ],
      "roles": [
        "data"
      ]
    },
    "swir22": {
      "href": "https://coclico.blob.core.windows.net/tmp/s2-l2a-composite/release/2025-01-17/22WES_z9-n65w051-73cc3d_20230101_20240101_swir22_10m.tif",
      "type": "image/tiff; application=geotiff; profile=cloud-optimized",
      "title": "swir22 band",
      "proj:code": "EPSG:32622",
      "proj:shape": [
        1640,
        3323
      ],
      "proj:transform": [
        10.0,
        0.0,
        517730.0,
        0.0,
        -10.0,
        7199730.0,
        0.0,
        0.0,
        1.0
      ],
      "proj:bbox": [
        517730.0,
        7183330.0,
        550960.0,
        7199730.0
      ],
      "proj:geometry": {
        "type": "Polygon",
        "coordinates": [
          [
            [
              550960.0,
              7183330.0
            ],
            [
              550960.0,
              7199730.0
            ],
            [
              517730.0,
              7199730.0
            ],
            [
              517730.0,
              7183330.0
            ],
            [
              550960.0,
              7183330.0
            ]
          ]
        ]
      },
      "raster:bands": [
        {
          "nodata": -9999,
          "data_type": "int16",
          "spatial_resolution": 10,
          "unit": "m",
          "scale": 0.0001
        }
      ],
      "roles": [
        "data"
      ]
    }
  },
  "collection": "s2-l2a-composite"
}