{
  "type": "Feature",
  "stac_version": "1.1.0",
  "stac_extensions": [
    "https://stac-extensions.github.io/projection/v2.0.0/schema.json",
    "https://stac-extensions.github.io/raster/v1.1.0/schema.json"
  ],
  "id": "46QFD_z9-n16e094-3d7033_20230101_20240101",
  "geometry": {
    "type": "Polygon",
    "coordinates": [
      [
        [
          94.22159485418547,
          16.188384489329326
        ],
        [
          94.22159485418547,
          16.632444229989584
        ],
        [
          94.11893561592444,
          16.632444229989584
        ],
        [
          94.11893561592444,
          16.188384489329326
        ],
        [
          94.22159485418547,
          16.188384489329326
        ]
      ]
    ]
  },
  "bbox": [
    94.11893561592441,
    16.188384489329326,
    94.22159485418545,
    16.632444229989584
  ],
  "properties": {
    "AREA_OR_POINT": "Area",
    "composite_avg_interval": "37 days 18:40:02.222222222",
    "composite_determination_method": "CoastPy Simple Median",
    "composite_n_obs": 10,
    "composite_stac_ids": "['S2B_MSIL2A_20230219T040819_R047_T46QFD_20230220T095132', 'S2A_MSIL2A_20230306T040631_R047_T46QFD_20230306T174359', 'S2B_MSIL2A_20230301T040709_R047_T46QFD_20240819T105051', 'S2B_MSIL2A_20230120T041059_R047_T46QFD_20230121T205446', 'S2B_MSIL2A_20230130T041019_R047_T46QFD_20230131T141849', 'S2B_MSIL2A_20231216T041149_R047_T46QFD_20231220T022054', 'S2A_MSIL2A_20230115T041121_R047_T46QFD_20230115T150817', 'S2A_MSIL2A_20230316T040541_R047_T46QFD_20240806T171410', 'S2B_MSIL2A_20230110T041129_R047_T46QFD_20230110T180000', 'S2A_MSIL2A_20231121T041051_R047_T46QFD_20231121T081700']",
    "composite_summary": "Composite dataset created by taking the median value of each pixel across all time steps.",
    "eo_cloud_cover": 0,
    "start_datetime": "2023-01-10T04:11:29.024000Z",
    "end_datetime": "2023-12-16T04:11:49.024000Z",
    "created": "2025-03-01T14:19:23.864133Z",
    "proj:code": "EPSG:32646",
    "proj:shape": [
      4907,
      1068
    ],
    "proj:transform": [
      10.0,
      0.0,
      619610.0,
      0.0,
      -10.0,
      1839230.0,
      0.0,
      0.0,
      1.0
    ],
    "proj:bbox": [
      619610.0,
      1790160.0,
      630290.0,
      1839230.0
    ],
    "proj:geometry": {
      "type": "Polygon",
      "coordinates": [
        [
          [
            630290.0,
            1790160.0
          ],
          [
            630290.0,
            1839230.0
          ],
          [
            619610.0,
            1839230.0
          ],
          [
            619610.0,
            1790160.0
          ],
          [
            630290.0,
            1790160.0
          ]
        ]
      ]
    },
    "datetime": "2023-01-10T04:11:29.024000Z"
  },
  "links": [
    {
      "rel": "root",
      "href": "../../catalog.json",
      "type": "application/json",
      "title": "CoCliCo STAC Catalog"
    },
    {
      "rel": "collection",
      "href": "../collection.json",
      "type": "application/json",
      "title": "Sentinel-2 L2A Annual Composites"
    },
    {
      "rel": "parent",
      "href": "../collection.json",
      "type": "application/json",
      "title": "Sentinel-2 L2A Annual Composites"
    }
  ],
  "assets": {
    "blue": {
      "href": "https://coclico.blob.core.windows.net/tmp/s2-l2a-composite/release/2025-01-17/46QFD_z9-n16e094-3d7033_20230101_20240101_blue_10m.tif",
      "type": "image/tiff; application=geotiff; profile=cloud-optimized",
      "title": "blue band",
      "proj:code": "EPSG:32646",
      "proj:shape": [
        4907,
        1068
      ],
      "proj:transform": [
        10.0,
        0.0,
        619610.0,
        0.0,
        -10.0,
        1839230.0,
        0.0,
        0.0,
        1.0
      ],
      "proj:bbox": [
        619610.0,
        1790160.0,
        630290.0,
        1839230.0
      ],
      "proj:geometry": {
        "type": "Polygon",
        "coordinates": [
          [
            [
              630290.0,
              1790160.0
            ],
            [
              630290.0,
              1839230.0
            ],
            [
              619610.0,
              1839230.0
            ],
            [
              619610.0,
              1790160.0
            ],
            [
              630290.0,
              1790160.0
            ]
          ]
        ]
      },
      "raster:bands": [
        {
          "nodata": -9999,
          "data_type": "int16",
          "spatial_resolution": 10,
          "unit": "m",
          "scale": 0.0001
        }
      ],
      "roles": [
        "data"
      ]
    },
    "green": {
      "href": "https://coclico.blob.core.windows.net/tmp/s2-l2a-composite/release/2025-01-17/46QFD_z9-n16e094-3d7033_20230101_20240101_green_10m.tif",
      "type": "image/tiff; application=geotiff; profile=cloud-optimized",
      "title": "green band",
      "proj:code": "EPSG:32646",
      "proj:shape": [
        4907,
        1068
      ],
      "proj:transform": [
        10.0,
        0.0,
        619610.0,
        0.0,
        -10.0,
        1839230.0,
        0.0,
        0.0,
        1.0
      ],
      "proj:bbox": [
        619610.0,
        1790160.0,
        630290.0,
        1839230.0
      ],
      "proj:geometry": {
        "type": "Polygon",
        "coordinates": [
          [
            [
              630290.0,
              1790160.0
            ],
            [
              630290.0,
              1839230.0
            ],
            [
              619610.0,
              1839230.0
            ],
            [
              619610.0,
              1790160.0
            ],
            [
              630290.0,
              1790160.0
            ]
          ]
        ]
      },
      "raster:bands": [
        {
          "nodata": -9999,
          "data_type": "int16",
          "spatial_resolution": 10,
          "unit": "m",
          "scale": 0.0001
        }
      ],
      "roles": [
        "data"
      ]
    },
    "nir": {
      "href": "https://coclico.blob.core.windows.net/tmp/s2-l2a-composite/release/2025-01-17/46QFD_z9-n16e094-3d7033_20230101_20240101_nir_10m.tif",
      "type": "image/tiff; application=geotiff; profile=cloud-optimized",
      "title": "nir band",
      "proj:code": "EPSG:32646",
      "proj:shape": [
        4907,
        1068
      ],
      "proj:transform": [
        10.0,
        0.0,
        619610.0,
        0.0,
        -10.0,
        1839230.0,
        0.0,
        0.0,
        1.0
      ],
      "proj:bbox": [
        619610.0,
        1790160.0,
        630290.0,
        1839230.0
      ],
      "proj:geometry": {
        "type": "Polygon",
        "coordinates": [
          [
            [
              630290.0,
              1790160.0
            ],
            [
              630290.0,
              1839230.0
            ],
            [
              619610.0,
              1839230.0
            ],
            [
              619610.0,
              1790160.0
            ],
            [
              630290.0,
              1790160.0
            ]
          ]
        ]
      },
      "raster:bands": [
        {
          "nodata": -9999,
          "data_type": "int16",
          "spatial_resolution": 10,
          "unit": "m",
          "scale": 0.0001
        }
      ],
      "roles": [
        "data"
      ]
    },
    "red": {
      "href": "https://coclico.blob.core.windows.net/tmp/s2-l2a-composite/release/2025-01-17/46QFD_z9-n16e094-3d7033_20230101_20240101_red_10m.tif",
      "type": "image/tiff; application=geotiff; profile=cloud-optimized",
      "title": "red band",
      "proj:code": "EPSG:32646",
      "proj:shape": [
        4907,
        1068
      ],
      "proj:transform": [
        10.0,
        0.0,
        619610.0,
        0.0,
        -10.0,
        1839230.0,
        0.0,
        0.0,
        1.0
      ],
      "proj:bbox": [
        619610.0,
        1790160.0,
        630290.0,
        1839230.0
      ],
      "proj:geometry": {
        "type": "Polygon",
        "coordinates": [
          [
            [
              630290.0,
              1790160.0
            ],
            [
              630290.0,
              1839230.0
            ],
            [
              619610.0,
              1839230.0
            ],
            [
              619610.0,
              1790160.0
            ],
            [
              630290.0,
              1790160.0
            ]
          ]
        ]
      },
      "raster:bands": [
        {
          "nodata": -9999,
          "data_type": "int16",
          "spatial_resolution": 10,
          "unit": "m",
          "scale": 0.0001
        }
      ],
      "roles": [
        "data"
      ]
    },
    "swir16": {
      "href": "https://coclico.blob.core.windows.net/tmp/s2-l2a-composite/release/2025-01-17/46QFD_z9-n16e094-3d7033_20230101_20240101_swir16_10m.tif",
      "type": "image/tiff; application=geotiff; profile=cloud-optimized",
      "title": "swir16 band",
      "proj:code": "EPSG:32646",
      "proj:shape": [
        4907,
        1068
      ],
      "proj:transform": [
        10.0,
        0.0,
        619610.0,
        0.0,
        -10.0,
        1839230.0,
        0.0,
        0.0,
        1.0
      ],
      "proj:bbox": [
        619610.0,
        1790160.0,
        630290.0,
        1839230.0
      ],
      "proj:geometry": {
        "type": "Polygon",
        "coordinates": [
          [
            [
              630290.0,
              1790160.0
            ],
            [
              630290.0,
              1839230.0
            ],
            [
              619610.0,
              1839230.0
            ],
            [
              619610.0,
              1790160.0
            ],
            [
              630290.0,
              1790160.0
            ]
          ]
        ]
      },
      "raster:bands": [
        {
          "nodata": -9999,
          "data_type": "int16",
          "spatial_resolution": 10,
          "unit": "m",
          "scale": 0.0001
        }
      ],
      "roles": [
        "data"
      ]
    },
    "swir22": {
      "href": "https://coclico.blob.core.windows.net/tmp/s2-l2a-composite/release/2025-01-17/46QFD_z9-n16e094-3d7033_20230101_20240101_swir22_10m.tif",
      "type": "image/tiff; application=geotiff; profile=cloud-optimized",
      "title": "swir22 band",
      "proj:code": "EPSG:32646",
      "proj:shape": [
        4907,
        1068
      ],
      "proj:transform": [
        10.0,
        0.0,
        619610.0,
        0.0,
        -10.0,
        1839230.0,
        0.0,
        0.0,
        1.0
      ],
      "proj:bbox": [
        619610.0,
        1790160.0,
        630290.0,
        1839230.0
      ],
      "proj:geometry": {
        "type": "Polygon",
        "coordinates": [
          [
            [
              630290.0,
              1790160.0
            ],
            [
              630290.0,
              1839230.0
            ],
            [
              619610.0,
              1839230.0
            ],
            [
              619610.0,
              1790160.0
            ],
            [
              630290.0,
              1790160.0
            ]
          ]
        ]
      },
      "raster:bands": [
        {
          "nodata": -9999,
          "data_type": "int16",
          "spatial_resolution": 10,
          "unit": "m",
          "scale": 0.0001
        }
      ],
      "roles": [
        "data"
      ]
    }
  },
  "collection": "s2-l2a-composite"
}