{
  "type": "Feature",
  "stac_version": "1.1.0",
  "stac_extensions": [
    "https://stac-extensions.github.io/table/v1.2.0/schema.json",
    "https://stac-extensions.github.io/projection/v2.0.0/schema.json"
  ],
  "id": "FR_50031",
  "geometry": {
    "type": "Polygon",
    "coordinates": [
      [
        [
          -1.64124455908071,
          49.35516232711747
        ],
        [
          -1.64124455908071,
          49.488315091129415
        ],
        [
          -1.825287167666388,
          49.488315091129415
        ],
        [
          -1.825287167666388,
          49.35516232711747
        ],
        [
          -1.64124455908071,
          49.35516232711747
        ]
      ]
    ]
  },
  "bbox": [
    -1.825287167666388,
    49.35516232711747,
    -1.64124455908071,
    49.488315091129415
  ],
  "properties": {
    "title": "CI_data",
    "description": "EU-wide high-resolution object-based maps of economic assets and infrastructure systems in coastal flood-prone areas.",
    "table:columns": [
      {
        "name": "type",
        "type": "string",
        "description": ""
      },
      {
        "name": "geometry",
        "type": "binary",
        "description": ""
      }
    ],
    "proj:bbox": [
      3468010.0639611967,
      2984437.653693952,
      3479420.7401063303,
      2997621.23670101
    ],
    "table:row_count": 5178,
    "created": "2025-04-08T10:33:57.765256Z",
    "datetime": "2021-08-01T00:00:00Z",
    "proj:code": "EPSG:3035"
  },
  "links": [
    {
      "rel": "root",
      "href": "https://minio.dive.edito.eu/project-coclico/coclico-stac-edito/catalog.json",
      "type": "application/json",
      "title": "CoCliCo STAC Catalog"
    },
    {
      "rel": "parent",
      "href": "https://minio.dive.edito.eu/project-coclico/coclico-stac-edito/ceed_maps/collection.json",
      "type": "application/json",
      "title": "Critical Infrastructure"
    },
    {
      "rel": "self",
      "href": "https://minio.dive.edito.eu/project-coclico/coclico-stac-edito/ceed_maps/items/FR_50031.json",
      "type": "application/json"
    },
    {
      "rel": "collection",
      "href": "https://minio.dive.edito.eu/project-coclico/coclico-stac-edito/ceed_maps/collection.json",
      "type": "application/json"
    }
  ],
  "assets": {
    "data": {
      "href": "gs://coclico-data-public/coclico/LAU_ceed/FR_50031.parquet",
      "type": "application/vnd.apache.parquet",
      "title": "CI_data",
      "description": "EU-wide high-resolution object-based maps of economic assets and infrastructure systems in coastal flood-prone areas.",
      "roles": [
        "data"
      ]
    },
    "visual": {
      "href": "https://coclico.avi.deltares.nl/geoserver/ceed_maps/wms?bbox={bbox-epsg-3857}&format=image/png&service=WMS&version=1.1.1&request=GetMap&srs=EPSG:3857&transparent=true&width=256&height=256&layers=ceed_maps:FR_50031",
      "type": "application/png",
      "title": "ceed_maps:FR_50031",
      "description": "OGS WMS url",
      "roles": [
        "visual"
      ]
    }
  },
  "collection": "ceed_maps"
}